PyClassicRound/PyClassicRound.py
PyClassicRound/__init__.py
PyClassicRound-2.2.dist-info/LICENSE
PyClassicRound-2.2.dist-info/METADATA
PyClassicRound-2.2.dist-info/WHEEL
PyClassicRound-2.2.dist-info/top_level.txt
PyClassicRound-2.2.dist-info/RECORD
