Metadata-Version: 2.1
Name: PyClassicRound
Version: 2.2
Summary: Current python 3's round function uses Banker's rounding, this package will help you to round off numbers the classical way.
Home-page: https://github.com/rohitxsh93/PyClassicRound
Author: Rohit
Author-email: rohit.shrivastava93@gmail.com
License: UNKNOWN
Platform: UNKNOWN
Classifier: Programming Language :: Python :: 3
Classifier: License :: OSI Approved :: MIT License
Classifier: Operating System :: OS Independent
Requires-Python: >=3.5
